odoo/addons/stock_return_request/README.rst
odoo/addons/stock_return_request/__init__.py
odoo/addons/stock_return_request/__manifest__.py
odoo/addons/stock_return_request/data/stock_return_request_data.xml
odoo/addons/stock_return_request/i18n/es.po
odoo/addons/stock_return_request/i18n/fr.po
odoo/addons/stock_return_request/i18n/it.po
odoo/addons/stock_return_request/i18n/pt_BR.po
odoo/addons/stock_return_request/i18n/pt_PT.po
odoo/addons/stock_return_request/i18n/stock_return_request.pot
odoo/addons/stock_return_request/models/__init__.py
odoo/addons/stock_return_request/models/stock_move.py
odoo/addons/stock_return_request/models/stock_picking.py
odoo/addons/stock_return_request/models/stock_return_request.py
odoo/addons/stock_return_request/readme/CONTRIBUTORS.md
odoo/addons/stock_return_request/readme/DESCRIPTION.md
odoo/addons/stock_return_request/readme/INSTALL.md
odoo/addons/stock_return_request/readme/ROADMAP.md
odoo/addons/stock_return_request/readme/USAGE.md
odoo/addons/stock_return_request/report/stock_return_report.xml
odoo/addons/stock_return_request/security/ir.model.access.csv
odoo/addons/stock_return_request/static/description/icon.png
odoo/addons/stock_return_request/static/description/index.html
odoo/addons/stock_return_request/tests/__init__.py
odoo/addons/stock_return_request/tests/test_stock_return_request.py
odoo/addons/stock_return_request/tests/test_stock_return_request_common.py
odoo/addons/stock_return_request/views/stock_return_request_views.xml
odoo/addons/stock_return_request/wizard/__init__.py
odoo/addons/stock_return_request/wizard/suggest_return_request.xml
odoo/addons/stock_return_request/wizard/suggest_return_request_lot.py
odoo_addon_stock_return_request-18.0.1.0.0.7.dist-info/METADATA
odoo_addon_stock_return_request-18.0.1.0.0.7.dist-info/WHEEL
odoo_addon_stock_return_request-18.0.1.0.0.7.dist-info/top_level.txt
odoo_addon_stock_return_request-18.0.1.0.0.7.dist-info/RECORD
